fuzzybunny.cpython-312-darwin.so
fuzzybunny-0.1.2.dist-info/RECORD
fuzzybunny-0.1.2.dist-info/WHEEL
fuzzybunny-0.1.2.dist-info/top_level.txt
fuzzybunny-0.1.2.dist-info/METADATA
fuzzybunny-0.1.2.dist-info/licenses/LICENSE
