Metadata-Version: 2.1
Name: fuzzybunny
Version: 0.1.2
Summary: A fuzzy search tool for python written in C++
Requires-Python: >=3.8
License-File: LICENSE
